yta_multimedia_core/__init__.py
yta_multimedia_core/audio/__init__.py
yta_multimedia_core/audio/frame.py
yta_multimedia_core/parser.py
yta_multimedia_core/video/__init__.py
yta_multimedia_core/video/frame/__init__.py
yta_multimedia_core/video/frame/extractor/__init__.py
yta_multimedia_core/video/frame/extractor/enums.py
yta_multimedia_core/video/frame/mask.py
yta_multimedia_core/video/frame/numpy.py
yta_multimedia_core/video/frame/t_handler.py
yta_multimedia_core/video/frame/validator.py
yta_multimedia_core/video/mp_video.py
yta_multimedia_core/video/video_wrapped.py
yta_multimedia_core-0.0.2.dist-info/LICENSE
yta_multimedia_core-0.0.2.dist-info/METADATA
yta_multimedia_core-0.0.2.dist-info/WHEEL
yta_multimedia_core-0.0.2.dist-info/RECORD
